filemoon/__init__.py
filemoon/filemoon.py
filemoon-0.2.6.dist-info/LICENSE.txt
filemoon-0.2.6.dist-info/METADATA
filemoon-0.2.6.dist-info/WHEEL
filemoon-0.2.6.dist-info/top_level.txt
filemoon-0.2.6.dist-info/RECORD
