Metadata-Version: 2.1
Name: filemoon
Version: 0.2.6
Summary: Unofficial python api wrapper from https://filemoon.sx/api
Home-page: https://github.com/BalaPriyan/filemoon
Author: balapriyan
Author-email: balapriyanbalusamy@gmail.com
Keywords: api,filemoon,video,hosting
Classifier: Development Status :: 3 - Alpha
Classifier: Programming Language :: Python :: 3
License-File: LICENSE.txt
Requires-Dist: requests
